{
    "data": {
      "answerlist": [
        { "index": 0, "answer": "回家" },
        { "index": 1, "answer": "别失望" },
        { "index": 2, "answer": "不必为你无法控制的事情担心" },
        { "index": 3, "answer": "不要忘记微笑" },
        { "index": 4, "answer": "阳光也许不会来了" },
        { "index": 5, "answer": "理想国" },
        { "index": 6, "answer": "平面人生" },
        { "index": 7, "answer": "资本论" },
        { "index": 8, "answer": "不要回头" },
        { "index": 9, "answer": "阿猫阿狗" },
        { "index": 10, "answer": "多读书" },
        { "index": 11, "answer": "会有好的结果的" },
        { "index": 12, "answer": "就这样吧" },
        { "index": 13, "answer": "来都来了" },
        { "index": 14, "answer": "猫猫不会抛下你的" },
        { "index": 15, "answer": "常常以为这是最后一刻" },
        { "index": 16, "answer": "你说呢" },
        { "index": 17, "answer": "无证之罪" },
        { "index": 18, "answer": "会有钱的" },
        { "index": 19, "answer": "王者还是亡者" },
        { "index": 20, "answer": "一步之遥" },
        { "index": 21, "answer": "js是一门很奇怪的语言" },
        { "index": 22, "answer": "操作系统" },
        { "index": 23, "answer": "所以呢？" },
        { "index": 22, "answer": "时间就是金钱" },
        { "index": 23, "answer": "金钱也是时间" }
      ]
    }
  }
  